aiomqttc.py
config.py
main.py
wifi.py
aiomqttc-1.0.7.dist-info/licenses/LICENSE
aiomqttc-1.0.7.dist-info/METADATA
aiomqttc-1.0.7.dist-info/WHEEL
aiomqttc-1.0.7.dist-info/top_level.txt
aiomqttc-1.0.7.dist-info/RECORD
