Metadata-Version: 2.4
Name: aiomqttc
Version: 1.0.7
Summary: aiomqttc - Asynchronous MQTT Client for Micropython and Python
Author-email: Carlos Tangerino <carlos.tangerino@gmail.com>
License-Expression: Unlicense
Project-URL: Homepage, https://github.com/Tangerino/aiomqttc.git
Project-URL: Documentation, https://github.com/Tangerino/aiomqttc.git
Project-URL: Source, https://github.com/Tangerino/aiomqttc.git
Project-URL: Issues, https://github.com/Tangerino/aiomqttc/issues
Keywords: micropython,mqtt,asyncio,iot,client,EDGE,aiomqttc
Classifier: Development Status :: 5 - Production/Stable
Classifier: Intended Audience :: Developers
Classifier: Natural Language :: English
Classifier: Programming Language :: Python :: 3.9
Classifier: Programming Language :: Python :: 3.10
Classifier: Programming Language :: Python :: 3.11
Classifier: Programming Language :: Python :: Implementation :: MicroPython
Classifier: Programming Language :: Python :: Implementation :: CPython
Classifier: Topic :: Software Development :: Embedded Systems
Classifier: Topic :: System :: Hardware
Classifier: Topic :: Communications
Classifier: Topic :: Internet
Requires-Python: >=3.9
License-File: LICENSE
Requires-Dist: rich>=14.0.0
Provides-Extra: dev
Requires-Dist: ruff>=0.4.0; extra == "dev"
Requires-Dist: pre-commit>=3.7.0; extra == "dev"
Dynamic: license-file
